confiture/__init__.py
confiture/parser.py
confiture/tree.py
confiture/schema/__init__.py
confiture/schema/containers.py
confiture/schema/types.py
confiture/tests/__init__.py
confiture/tests/test_parser.py
confiture-2.1.dist-info/DESCRIPTION.rst
confiture-2.1.dist-info/METADATA
confiture-2.1.dist-info/RECORD
confiture-2.1.dist-info/WHEEL
confiture-2.1.dist-info/metadata.json
confiture-2.1.dist-info/top_level.txt
confiture-2.1.dist-info/zip-safe
